mbot/__init__.py
mbot/bot.py
mbot/cli.py
mbot/config.py
mbot/decorators.py
mbot/dialog.py
mbot/event.py
mbot/exceptions.py
mbot/middleware.py
mbot/state.py
mbot/storage.py
mbot-0.0.2.dist-info/DESCRIPTION.rst
mbot-0.0.2.dist-info/METADATA
mbot-0.0.2.dist-info/RECORD
mbot-0.0.2.dist-info/WHEEL
mbot-0.0.2.dist-info/entry_points.txt
mbot-0.0.2.dist-info/metadata.json
mbot-0.0.2.dist-info/top_level.txt
