Metadata-Version: 2.0
Name: mbot
Version: 0.0.2
Summary: Yet another Bot implemented in pure Python.
Home-page: https://github.com/michaelkuty/sbot
Author: Michael Kutý
Author-email: 6du1ro.n@gmail.com
License: MIT license
Keywords: mbot
Platform: UNKNOWN
Classifier: Development Status :: 2 - Pre-Alpha
Classifier: Intended Audience :: Developers
Classifier: License :: OSI Approved :: MIT License
Classifier: Natural Language :: English
Classifier: Programming Language :: Python :: 2
Classifier: Programming Language :: Python :: 2.6
Classifier: Programming Language :: Python :: 2.7
Classifier: Programming Language :: Python :: 3
Classifier: Programming Language :: Python :: 3.3
Classifier: Programming Language :: Python :: 3.4
Classifier: Programming Language :: Python :: 3.5
Requires-Dist: Click (>=6.0)
Requires-Dist: PyYAML
Requires-Dist: anyconfig
Requires-Dist: appdirs
Requires-Dist: asyncio
Requires-Dist: dill
Requires-Dist: humanize
Requires-Dist: parsedatetime
Requires-Dist: slugify
Requires-Dist: typing
